tubao_utils/__init__.py
tubao_utils-0.0.1.dist-info/LICENSE
tubao_utils-0.0.1.dist-info/METADATA
tubao_utils-0.0.1.dist-info/WHEEL
tubao_utils-0.0.1.dist-info/top_level.txt
tubao_utils-0.0.1.dist-info/RECORD
