Metadata-Version: 2.1
Name: tubao-utils
Version: 0.0.1
Summary: Utils package
Home-page: https://github.com/hyc3z/utils
Author: Hyc3z
Author-email: tubao9hao@126.com
License: UNKNOWN
Platform: UNKNOWN
Classifier: Programming Language :: Python :: 3
Classifier: License :: OSI Approved :: MIT License
Classifier: Operating System :: OS Independent
License-File: LICENSE
